<?xml version="1.0" encoding="utf-8" ?>
<dwsync>
<file name="logo_cmd_blue_landscape.jpg" server="alfa3062.alfahosting-server.de//html/business/projects/comand-cms/development/" local="132132729628075500" remote="132170102400000000" Dst="1" />
<file name="logo_cmd_blue_landscape_large.jpg" server="alfa3062.alfahosting-server.de//html/business/projects/comand-cms/development/" local="132133752166806478" remote="132170102400000000" Dst="1" />
<file name="logo_cmd_blue_portrait.jpg" server="alfa3062.alfahosting-server.de//html/business/projects/comand-cms/development/" local="132132730188424609" remote="132170102400000000" Dst="1" />
<file name="logo_cmd_green_landscape.jpg" server="alfa3062.alfahosting-server.de//html/business/projects/comand-cms/development/" local="132132729835295866" remote="132170102400000000" Dst="1" />
<file name="logo_cmd_green_portrait.jpg" server="alfa3062.alfahosting-server.de//html/business/projects/comand-cms/development/" local="132132730348022420" remote="132170102400000000" Dst="1" />
<file name="logo_cmd_red_landscape.jpg" server="alfa3062.alfahosting-server.de//html/business/projects/comand-cms/development/" local="132132729760182256" remote="132170102400000000" Dst="1" />
<file name="logo_cmd_red_portrait.jpg" server="alfa3062.alfahosting-server.de//html/business/projects/comand-cms/development/" local="132132730267088810" remote="132170102400000000" Dst="1" />
<file name="logo_cmd_yellow_landscape.jpg" server="alfa3062.alfahosting-server.de//html/business/projects/comand-cms/development/" local="132132729943668535" remote="132170102400000000" Dst="1" />
<file name="logo_cmd_yellow_portrait.jpg" server="alfa3062.alfahosting-server.de//html/business/projects/comand-cms/development/" local="132132730457126954" remote="132170102400000000" Dst="1" />
</dwsync>